[
  {
    "question":  "The moment of inertia of a rod of mass <i>m</i> and length <i>l</i> about an axis perpendicular to its length and passing through its centre is"
  ,
    "options": [
      "\\frac{m l^2}{3}",
      "\\frac{m l^2}{12}",
      "\\frac{m l^2}{4}",
      "m l^{2}"
    ],
    "answer": "\\frac{m l^2}{12}",
    "tags": {
      "chapter": "Rotational Motion",
      "difficulty": "easy",
      "class": "11"
    },
    "tip": ""
  },
  {
    "question":  "The moment of inertia of a rod of mass <i>m</i> and length <i>l</i> about an axis perpendicular to its length and passing through its end is"
  ,
    "options": [
      "\\frac{m l^2}{3}",
      "\\frac{m l^2}{12}",
      "\\frac{m l^2}{4}",
      "m l^{2}"
    ],
    "answer": "\\frac{m l^2}{3}",
    "tags": {
      "chapter": "Rotational Motion",
      "difficulty": "easy",
      "class": "11"
    },
    "tip": ""
  }
]
